Workbook

Sheet Page de garde
C3: République Gabonaise
C4: Union - Travail - Justice
A6: Owendo le 30 septembre 2025
A8: RECAPITULATIF TRAVAUX D'AMENAGEMENT DES VOIRIES DE DESSERTE DU QUARTIER AKEMIDJOGONI
A11: VOIES A CONSTRUIRE (6 axes)
A13: Longueur Totale des axes = 1,28126 km (1281,26ml)
A14: RdPoint-LéonMBA=445,46ml / RP-KOMO=115,84ml / Marine-RP=112,60ml / RP-Patrimoine=448,30ml / Amorce BSP=52,00ml / RP-MontagneSte=107,36ml
A16: ASSAINISSEMENT
A18: BASSINS VERSANTS
A19: Longueur = 2136,65 ml
A20: CANIVEAUX
A21: Longueur = 1295 ml
A22: DALOTS
A23: Longueur = 80,4 ml
A26: Devis n° GAO/PRZ/70/30/09/25 du 30/09/2025
A27: N° | B27: Désignation | C27: Unité | D27: Quantité | E27: Prix Unitaire | F27: Montant
A28: 00 - INSTALLATION & ETUDES | H28: =760+1390 -> 2150 | J28: 2136.65 | K28: 3431.65 | L28: 80.4 | M28: 1295
A29: 101-1 | B29: Installation de chantier, amenée et repli du matériel | C29: Fft | D29: 1 | E29: ='Nouveau DQE'!I18 -> 60730000 | F29: =+E29*D29 -> 60730000 | J29: BV | K29: DRAINAGE | L29: Dalots | M29: Can
A30: 101-2 | B30: HESS (Hygiène, Environnement, Santé, Sécurité) | C30: FT | D30: 1 | E30: ='Nouveau DQE'!I19 -> 20410000 | F30: =E30*D30 -> 20410000
A31: 102 | B31: Etudes | C31: Fft | D31: 1 | E31: =SUM('Nouveau DQE'!G21:G26) -> 79920000 | F31: =+E31*D31 -> 79920000
A32: 108 | B32: Déplacement des réseaux (élec + eau + télécoms) | C32: Fft | D32: 1 | E32: =SUM('Nouveau DQE'!G46,'Nouveau DQE'!G73,'Nouveau DQE'!G190) -> 1.6407792e+08 | F32: =+E32*D32 -> 1.6407792e+08
A34: 00- RECAP DES INSTALLATIONS - TRAVAUX PREPARATOIRES - ETUDES & DEPLACEMENT DES RESEAUX | F34: =SUM(F29:F33) -> 3.2513792e+08 | G34: =F34/$K$34/8*7 -> 2.2204368e+08 | H34: =G34/G59 -> 0.083608023 | K34: 1.28126 | L34: Km
A36: 3000 - RECAP DES TRAVAUX DE CONSTRUCTION DES ROUTES (1,28126km ou 1281,26ml) | F36: ='Nouveau DQE'!G316 -> 1.583424e+09 | G36: =F36/$K$34/8*7 -> 1.0813543e+09 | K36: =F36/K34 -> 1.2358335e+09 | L36: km moyen/voirie
A37: Récap des items maintenus, avec anciens prix, mais quantités supérieures | F37: =SUM('Nouveau DQE'!I289,'Nouveau DQE'!I295:I297,) -> 4.1541797e+08 | G37: =F37/$K$34/8*7 -> 2.8369786e+08 | H37: =G37/$G$59 -> 0.10682321
A39: Récap des items maintenus avec anciens prix et quantités inférieures | F39: =SUM('Nouveau DQE'!I309,'Nouveau DQE'!I303:I307,'Nouveau DQE'!I290) -> 1.0425221e+09 | G39: =F39/$K$34/8*7 -> 7.1196076e+08 | H39: =G39/$G$59 -> 0.26808073
A41: Récap des nouveaux prix | F41: =SUM('Nouveau DQE'!I291,'Nouveau DQE'!I298) -> 1.2548395e+08 | G41: =F41/$K$34/8*7 -> 85695685 | H41: =G41/$G$59 -> 0.032267736 | K41: =F41+F39+F37 -> 1.583424e+09
A43: 500 - Recap des BASSINS VERSANTS & ASSAINISSEMENTS DIVERS | F43: =+F44+F46+F48 -> 1590529039 | G43: =F43/$K$34/8*7 -> 1.0862065e+09
A44: Récap des items maintenus, avec anciens prix, mais quantités supérieures | F44: =+'Nouveau DQE'!J440 -> 106427650 | G44: =F44/$K$34/8*7 -> 72681730 | H44: =G44/$G$59 -> 0.027367479
A46: Récap des items maintenus avec anciens prix et quantités inférieures | F46: =+'Nouveau DQE'!J425 -> 2816640 | G46: =F46/$K$34/8*7 -> 1923544 | H46: =G46/$G$59 -> 0.00072428863
A48: Récap des nouveaux prix | F48: =+'Nouveau DQE'!J346 -> 1481284749 | G48: =F48/$K$34/8*7 -> 1.0116012e+09 | H48: =G48/$G$59 -> 0.38090693
A50: RECAP BUDGET DES INDEMNISATIONS HORS CHIFFRAGE MIKA SERVICES ET AMENAGEMENTS SPECIFIQUES | F50: =SUM(F51:F57) -> 3.8974541e+08 | G50: =F50/$K$34/8*7 -> 2.6616552e+08 | L50: =G50/$G$59 -> 0.1002216
A51: A - Enveloppe des expropriations, droits de passages sur terrains, démolition&reconstructions des barrières | F51: =+'Nouveau DQE'!G562 -> 50874162 | G51: =F51/$K$34/8*7 -> 34743059 | H51: =G51/$G$59 -> 0.013082104
A53: B - Amenagement divers plateaux sportifs / parking | F53: =+'Nouveau DQE'!G573 -> 230000000 | G53: =F53/$K$34/8*7 -> 1.5707194e+08 | H53: =G53/$G$59 -> 0.059143655
A55: C - Autres aménagements | F55: =+'Nouveau DQE'!G575 -> 83871250 | G55: =F55/$K$34/8*7 -> 57277480 | H55: =G55/$G$59 -> 0.021567184
A57: D - Aménagements et/ou dévoiements de réseaux non prévus | F57: =+'Nouveau DQE'!G620 -> 25000000 | G57: =F57/$K$34/8*7 -> 17073037 | H57: =G57/$G$59 -> 0.0064286582
A59: TOTAL HTVA | F59: =ROUNDUP(+F50+F43+F36+F34,0) -> 3888836403 | G59: =F59/$K$34/8*7 -> 2.65577e+09 | H59: =+SUM(H57,H55,H53,H51,H48,H46,H44,H41,H39,H37,H36,H34) -> 1 | L59: Moyenne 1,2Mds/km
A60: CCS (1%) | F60: =+F59*0.01 -> 38888364
A61: TVA (18%) | F61: =+F59*0.18 -> 6.9999055e+08
A62: TOTAL GENERAL TTC | F62: =SUM(F59:F61) -> 4.6277153e+09
A63: Code couleur
A64: Ancien item avec prix pour mémoire , mais quantités à la hausse
A65: Ancien item avec prix pour mémoire ; mais quantités inférieures
A66: Nouveaux prix
B68: Administrateur Directeur Général - Mika Services
B70: Patrice Revangue Zavrosa
A72: Arrêté le présent DQE à la somme TTc de ; Quatre milliards, six-cent-vingt-sept millions, sept-cent-quinze mille, trois-cent-vingt francs CFA
F102: 95000
F103: 30000
F114: 28000
G151: =SUM(G138,G126,G114,G104,G103,G153,G102,G101,G96,G88,G77,#REF!,#REF!+G147) -> #REF!
F153: 90000
F168: 190000000
G184: =SUM(G153,G158,G162,G168,G174,G179,G180) -> 0
F185: DORSALE / Emprise 10ml / voie 7m + 2*1,5ml trottoirs | G185: =G184+G151 -> #REF!
A187: RESEAU DE ROUTES PENETRANTES / Emprise 8ml/ voie 6ml + 2*1ml trottoirs
A298: 502
A303: 503
F304: Sous total aménagement | G304: =G282+G298+G303 -> 0
F306: Sous Total RESEAU DE ROUTES PENETRANTES / Emprise 8ml/ voie 6ml + 2*1ml trottoirs | G306: =G304+G280 -> 0
A308: Frais divers réseaux et dédommagement
B309: Enveloppe déplacement des réseaux enterrés (eau) routes pénétrantes
B310: Enveloppe déplacement des supports aériens Routes pénétrantes
A311: 303
B313: Enveloppe de compensations bâtisses à reculer sur DORSALE
B314: Enveloppe de compensations bâtisses rtéseau routes pénétrantes
B318: Enveloppe de désenclament des zones sous-intégrées routes pénétrantes
A321: Frais divers réseaux et dédommagement | G321: =G309+G310+G311+G312+G313+G314+G318 -> 0
G322: =G321+G306+G185+G72 -> #REF!

Sheet Nouveau DQE
E2: République Gabonaise
E3: Union - Travail - Justice | I3: ancien + qté sup
I4: ancien + qté inf | N4: coef. Vente | O4: FFx | P4: Terr. | Q4: BAC+ Ass.
I5: nouveau prix | O5: 1.15 | P5: 1.3 | Q5: 1.4
A6: DEVIS QUANTITATIF ESTIMATIF
A7: TRAVAUX D'AMENAGEMENT DES VOIRIES DE DESSERTE DU QUARTIER AKEMIDJOGONI | K7: Excédent - HT
A9: Structure de chaussée : Enrochement de blocs létéritiques 400/600/800 + Graveleux Latétéritique GL0/25=0,25m en consolidation pour couche de forme + Fondation en grave non traitée GNT 0/25 = 0,20m + Béton Armé Continu (BAC) épaisseur 0,15m en base-roulement + 2*1,5ml de trottoir + bassin versant&allée contigue + parking+ terrain de sport | K9: =O557 -> -0.2938314
A10: Linéaire chaussée en béton armé continu BAC = 1281,26ml _//_ Linéaire cumulé d'ouvrages d'assainissements (Bassins versants/canal/exutoires/ouvrages hydrauliques/dalots) = 3512,05ml | K10: =E283 -> 1281.26 | L10: =SUM(E346,E362,E363,E378,E393,E394,E410,E425,E440,E442,E443,E444,E459,E474,E476,E477,E496,E497,E515,E534,E553) -> 3512.05
A12: PROJET AKEMIDJOGONI
A14: Devis n° GAO/PRZ/70/30/09/25 du 30/09/2025
A15: N° Prix | B15: Désignation | C15: Unités | D15: Nb | E15: Quantités | F15: Prix unitaire | G15: Prix total | K15: brut | L15: Peines & soins | M15: cdc | N15: DS/revient | O15: VENTE | P15: marge
A16: Chapitre 100 - Travaux Préparatoires | L16: 0.1 | M16: 0.02
A17: 101 | B17: Frais fixes | C17: FT | D17: 1 | E17: 1
A18: 101-1 | B18: Installation de chantier - A/R personnel et matériel | C18: FT | D18: 1 | E18: 1 | F18: =60730000 -> 60730000 | G18: =F18*E18 -> 60730000 | I18: =G18 -> 60730000 | K18: 35000000 | L18: =K18*$L$16 -> 3500000 | M18: =K18*$M$16 -> 700000 | N18: =SUM(K18:M18) -> 39200000 | O18: =N18*$O$5 -> 45080000 | P18: =O18-N18 -> 5880000
A19: 101-2 | B19: Enveloppe QHSE | C19: FT | D19: 1 | E19: 1 | F19: =20410000 -> 20410000 | G19: =F19*E19 -> 20410000 | I19: =G19 -> 20410000 | K19: 4000000 | L19: =K19*$L$16 -> 400000 | M19: =K19*$M$16 -> 80000 | N19: =SUM(K19:M19) -> 4480000 | O19: =N19*$O$5 -> 5152000 | P19: =O19-N19 -> 672000
A20: =A17+1 -> 102 | B20: Etudes | C20: FT | D20: 1 | E20: 1
A21: 102;1 | B21: Process documentaire | C21: FT | D21: 1 | E21: 1 | F21: =10400000 -> 10400000 | G21: =F21*E21 -> 10400000 | I21: =SUM(G21:G26) -> 79920000
A22: 102;2 | B22: Etudes topo | C22: FT | D22: 1 | E22: 1 | F22: 18280000 | G22: =F22*E22 -> 18280000
A23: 102;3 | B23: Etudes géotechniques | C23: FT | D23: 1 | E23: 1 | F23: 29860000 | G23: =F23*E23 -> 29860000
A24: 102;4 | B24: Elaboration Dossier constructeur/EXE + DFA | C24: FT | D24: 1 | E24: 1 | F24: =3600000 -> 3600000 | G24: =F24*E24 -> 3600000
A25: 102;5 | B25: Hydraulique - Hydraologie - Assainissement | C25: FT | D25: 1 | E25: 1 | F25: =MROUND(O25,20000) -> 10040000 | G25: =F25*E25 -> 10040000 | K25: 8300000 | L25: =K25*$L$16 -> 830000 | M25: =K25*$M$16 -> 166000 | N25: =SUM(K25:M25) -> 9296000 | O25: =N25*$Q$25 -> 10039680 | P25: =O25-N25 -> 743680 | Q25: 1.08
A26: 102;6 | B26: NIES | C26: FT | D26: 1 | E26: 1 | F26: =MROUND(O26,20000) -> 7740000 | G26: =F26*E26 -> 7740000 | K26: 6400000 | L26: =K26*$L$16 -> 640000 | M26: =K26*$M$16 -> 128000 | N26: =SUM(K26:M26) -> 7168000 | O26: =N26*$Q$25 -> 7741440 | P26: =O26-N26 -> 573440
A27: =A20+1 -> 103 | B27: Néttoyage et décapage du site | C27: m² | D27: 1 | E27: =E28 -> 23983 | F27: =MROUND(O27,5) -> 1110 | G27: Pour mémoire | K27: =SUM(G28:G37)/$E27 -> 861.54734 | L27: =K27*$L$16 -> 86.154734 | M27: =K27*$M$16 -> 17.230947 | N27: =SUM(K27:M27) -> 964.93302 | O27: =N27*$O$5 -> 1109.673 | P27: =O27-N27 -> 144.73995
B28: Surface cible = 23,983m² | C28: fft | D28: 1 | E28: =23983 -> 23983
B29: volume = 23,893 * 0,2 | C29: m² | D29: 1 | E29: =E28*0.2 -> 4796.6
B30: Pelle (40 camions/jr) | C30: u | D30: =MROUND(E29/(12*40),0.05) -> 10 | E30: 1 | F30: =7500000/26 -> 288461.54 | G30: =F30*E30*D30 -> 2884615.4
B31: bull | C31: u | D31: =D30 -> 10 | E31: =E30 -> 1 | F31: =7500000/26 -> 288461.54 | G31: =F31*E31*D31 -> 2884615.4
B32: niveleuse | C32: u | D32: =D31 -> 10 | E32: 1 | F32: =8000000/26 -> 307692.31 | G32: =F32*E32*D32 -> 3076923.1
B33: Gasoil engins | C33: lt | D33: =D31 -> 10 | E33: =SUM(E30:E32)*100 -> 300 | F33: =1045 -> 1045 | G33: =F33*E33*D33 -> 3135000
B34: camion benne + chauffeur + GO | C34: u | D34: =D32 -> 10 | E34: 4 | F34: =200000/1.095 -> 182648.4 | G34: =F34*E34*D34 -> 7305936.1
B35: Conducteur engins | C35: Unités | D35: =D30 -> 10 | E35: =SUM(E30:E32) -> 3 | F35: =MROUND((350000/176.33)*1.225*12,10) -> 29180 | G35: =F35*E35*D35 -> 875400
B36: HTM | C36: Unités | D36: =D30 -> 10 | E36: =1+E35 -> 4 | F36: =MROUND((150000/176.33)*1.225*12,10) -> 12500 | G36: =F36*E36*D36 -> 500000
A38: =A27+1 -> 104 | B38: Compteur eau à déplacer | C38: Unités | D38: 1 | E38: 44 | F38: 210000 | G38: Pour mémoire | Q38: ATTENTE MOUSSA !!!!!
A39: =A38+1 -> 105 | B39: Poste de Transformateur électrique à déplacer | C39: Unités | D39: 1 | E39: 1 | F39: 17710000 | G39: Pour mémoire
A40: =A39+1 -> 106 | B40: Poteau électrique Basse Tensions (BT) à déplacer | C40: Unités | D40: 1 | E40: 7 | F40: 5390000 | G40: Pour mémoire
A41: =A40+1 -> 107 | B41: Poteau électrique Haute Tensions (HT) à déplacer | C41: Unités | D41: 1 | E41: 3 | F41: 7080000 | G41: Pour mémoire
A42: 108 | B42: Déplacement des réseaux
A43: 108.1 | B43: Travaux préparatoires
A44: 101 | B44: Installation de chantier / Mobilisation et démobilisation d'équipe / Repli | C44: ens | D44: 1 | E44: 1 | F44: =MROUND(K44/$M$49,10) -> 3146070 | G44: =F44*E44*D44 -> 3146070 | J44: 3733330 | K44: =500000+500000+500000+500000+200000+200000+200000+200000 -> 2800000 | L44: =L42*K44 -> 0 | M44: =K44/M42 -> #DIV/0! | N44: =1-K44/L44 -> #DIV/0! | O44: =1-K44/M44 -> #DIV/0! | P44: =F44/K44 -> 1.1235964
A45: 102 | B45: Panneaux de signalisation / Balisage | C45: ens | D45: 1 | E45: 1 | F45: =MROUND(K45/$M$49,10) -> 2786520 | G45: =F45*E45*D45 -> 2786520 | J45: 3348000 | K45: =240000+240000+300000+200000+300000+200000+300000+200000+300000+200000 -> 2480000
B46: Installation spécifique, affichages, gestion de process consignation/déconsignation | C46: ens | D46: 1 | E46: 1 | F46: =G46 -> 5932590 | G46: =SUM(G44:G45) -> 5932590 | I46: =SUM(G46,G73,G190) -> 1.6407792e+08 | K46: Télécom? | L46: ???
A47: 108.2 | B47: EAU | K47: Bretelles MS + KOMO
A48: 201 | B48: LOT 1 : PL 700-302-N02 AU PL 560-203
A49: 201-0 | B49: mob + signalétique | C49: Fft | E49: 1 | F49: =MROUND(K49/$M$49,10) -> 831460 | G49: =F49*E49 -> 831460 | J49: =G49 -> 831460 | K49: =500000+240000 -> 740000 | L49: ok | M49: 0.89 | N49: =G49/K49 -> 1.1235946
A50: 201-1 | B50: Ouverture de tranchée pour la canalisation DN50EEHD de section 07x1,37x75 | C50: Fft | E50: 1 | F50: =MROUND(K50/$M$49,10) -> 2022470 | G50: =F50*E50 -> 2022470 | J50: 2430000 | K50: 1800000 | L50: ok
A51: 201-2 | B51: Fourniture et mise en œuvre du sable de remblai | C51: Fft | E51: 1 | F51: =MROUND(K51/$M$49,10) -> 2123600 | G51: =F51*E51 -> 2123600 | J51: 2551500 | K51: 1890000 | L51: ok
A52: 201-3 | B52: Déplacement des branchements eau DN50 PEHD | C52: Fft | E52: 1 | F52: =MROUND(K52/$M$49,10) -> 7752810 | G52: =F52*E52 -> 7752810 | J52: 9315000 | K52: 6900000 | L52: ok
A53: 201-4 | B53: Déplacement des branchements eau DN25 PEHD | C53: Fft | E53: 1 | F53: =MROUND(K53/$M$49,10) -> 18651690 | G53: =F53*E53 -> 18651690 | J53: 22410000 | K53: 16600000 | L53: ok
A54: 201-5 | B54: Supression branchement existant DN20/40 y compris fourniture accessoire | C54: Fft | E54: 1 | F54: =MROUND(K54/$M$49,10) -> 1123600 | G54: =F54*E54 -> 1123600 | J54: 1350000 | K54: 1000000 | L54: ok | M54: =SUM(K49:K54) -> 28930000
A55: 202 | B55: LOT 2 : PL 124-201 AU PL 416-101-N04
A56: 201-0 | B56: mob + signalétique | C56: Fft | E56: 1 | F56: =MROUND(K56/$M$49,10) -> 831460 | G56: =F56*E56 -> 831460 | J56: =G56 -> 831460 | K56: =500000+240000 -> 740000 | L56: ok
A57: 202-1 | B57: Ouverture de tranchée pour la canalisation DN50EEHD de section 07x1,37x23 | C57: Fft | E57: 1 | F57: =MROUND(K57/$M$49,10) -> 258430 | G57: =F57*E57 -> 258430 | J57: 310500 | K57: 230000 | L57: ok
A58: 202-2 | B58: Fourniture et mise en œuvre du sable de remblai | C58: Fft | E58: 1 | F58: =MROUND(K58/$M$49,10) -> 361800 | G58: =E58*F58 -> 361800 | J58: 434700 | K58: 322000 | L58: ok
A59: 202-3 | B59: Déplacement des branchements eau DN50 PEHD | C59: Fft | E59: 1 | F59: =MROUND(K59/$M$49,10) -> 7752810 | G59: =E59*F59 -> 7752810 | J59: 9315000 | K59: 6900000 | L59: ok
A60: 202-4 | B60: Déplacement des branchements eau DN25 PEHD | C60: Fft | E60: 1 | F60: =MROUND(K60/$M$49,10) -> 4494380 | G60: =E60*F60 -> 4494380 | J60: 5400000 | K60: 4000000 | L60: ok
A61: 202-5 | B61: Déplacement des branchements galva existant DN20/27 y compris fourniture accessoires | C61: Fft | E61: 1 | F61: =MROUND(K61/$M$49,10) -> 2696630 | G61: =E61*F61 -> 2696630 | J61: 3240000 | K61: 2400000 | L61: ok
A62: 202-6 | B62: Déplacement des branchements galva existant DN40/49 y compris fourniture accessoires | C62: Fft | E62: 1 | F62: =MROUND(K62/$M$49,10) -> 561800 | G62: =E62*F62 -> 561800 | J62: 675000 | K62: 500000 | L62: ok | M62: =SUM(K56:K62) -> 15092000
A63: 203 | B63: LOT 3 : PL 590-203-AO1
A64: 201-0 | B64: mob + signalétique | C64: Fft | E64: 1 | F64: =MROUND(K64/$M$49,10) -> 561800 | G64: =F64*E64 -> 561800 | J64: =G64 -> 561800 | K64: =500000*E64 -> 500000 | L64: ok
A65: 203-1 | B65: Déplacement des branchements eau DN50 PEHD | C65: U | E65: 10 | F65: =MROUND(K65/$M$49,10) -> 3370790 | G65: =E65*F65 -> 33707900 | J65: 405000 | K65: =300000*E65 -> 3000000 | L65: ok
A66: 203-2 | B66: Suppression de branchement PEHD existant DN50 y compris fourniture d'accessoires | C66: U | E66: 2 | F66: =MROUND(K66/$M$49,10) -> 337080 | G66: =E66*F66 -> 674160 | J66: 202500 | K66: =150000*E66 -> 300000 | L66: ok | M66: =SUM(K64:K66) -> 3800000
A67: 204 | B67: LOT 4 : PL 416-101-NO4
A68: 201-0 | B68: mob + signalétique | C68: Fft | E68: 1 | F68: =MROUND(K68/$M$49,10) -> 561800 | G68: =F68*E68 -> 561800 | J68: =G68 -> 561800 | K68: =500000*E68 -> 500000 | L68: ok
A69: 204-1 | B69: Déplacement des branchements eau DN50 PEHD | C69: U | E69: 2 | F69: =MROUND(K69/$M$49,10) -> 674160 | G69: =E69*F69 -> 1348320 | J69: 405000 | K69: =300000*E69 -> 600000
A70: 204-2 | B70: Déplacement des branchements galva existant DN20/27 y compris fourniture accessoires | C70: U | E70: 1 | F70: =MROUND(K70/$M$49,10) -> 269660 | G70: =E70*F70 -> 269660 | J70: 324000 | K70: =240000*E70 -> 240000 | M70: =SUM(K68:K70) -> 1340000
A71: xxx | B71: Déduction à prix coûtant axe 7 | C71: ens | D71: 1 | E71: -150 | F71: =+$L$73 -> 21303.533 | G71: =F71*E71*D71 -> -3195530 | L71: REPERCUSSION DE PRIX AU ML à 65% pour eau
A72: yyy | B72: déduction à prix coûtant axe 2 | C72: ens | D72: 1 | E72: =-250 -> -250 | F72: =F71 -> 21303.533 | G72: =F72*E72*D72 -> -5325883.3
B73: Travaux de dévoiements divers & mise en conformité du réseau | C73: ens | D73: 1 | E73: 1 | F73: =G73 -> 78065167 | G73: =SUM(G49:G72) -> 78065167 | J73: =SUM(J49:J70) -> 61554720 | K73: =SUM(K49:K70) -> 49162000 | L73: =(K73/1500)*0.65 -> 21303.533
A74: 108.3 | B74: ELECTRICITE & Télecoms
A75: 301 | B75: Carrefour Léon Mba - Rond Point Marine Nationale - Rond Point Sapeurs Pompiers
A76: 201-0 | B76: installation + signalisation + repli | C76: Fft | E76: 1 | F76: =MROUND(K76/$M$49,10) -> 786520 | G76: =F76*E76 -> 786520 | J76: =G76 -> 786520 | K76: =300000+200000+200000 -> 700000 | L76: =K76*E76 -> 700000
A77: 301-1 | B77: Fourniture support métallique 10-930 | C77: U | E77: 11 | F77: =MROUND(K77/$M$49,10) -> 624160 | G77: =E77*F77 -> 6865760 | J77: 749930 | K77: 555500 | L77: =K77*E77 -> 6110500
A78: 301-2 | B78: Fourniture support métallique 10.440 | C78: U | E78: 6 | F78: =MROUND(K78/$M$49,10) -> 399440 | G78: =E78*F78 -> 2396640 | J78: 479930 | K78: 355500 | L78: =K78*E78 -> 2133000
A79: 301-3 | B79: Fourniture câble torsadé 3 x 70 + 54,6 + 2 x 16mm² | C79: ml | E79: 550 | F79: =MROUND(K79/$M$49,10) -> 7870 | G79: =E79*F79 -> 4328500 | J79: 9450 | K79: 7000 | L79: =K79*E79 -> 3850000
A80: 301-4 | B80: Fourniture câble torsadé 2 x 25 | C80: ml | E80: 500 | F80: =MROUND(K80/$M$49,10) -> 1120 | G80: =E80*F80 -> 560000 | J80: 1350 | K80: 1000 | L80: =K80*E80 -> 500000
A81: 301-5 | B81: Fourniture KZ 95/95 + JZ 16/95 | C81: ens | E81: 1 | F81: =MROUND(K81/$M$49,10) -> 442130 | G81: =E81*F81 -> 442130 | J81: 531230 | K81: 393500 | L81: =K81*E81 -> 393500
A82: 301-6 | B82: Fourniture ES | C82: u | E82: 13 | F82: =MROUND(K82/$M$49,10) -> 9550 | G82: =E82*F82 -> 124150 | J82: 11480 | K82: 8500 | L82: =K82*E82 -> 110500
A83: 301-7 | B83: Fourniture EADS | C83: u | E83: 12 | F83: =MROUND(K83/$M$49,10) -> 21910 | G83: =E83*F83 -> 262920 | J83: 26330 | K83: 19500 | L83: =K83*E83 -> 234000
A84: 301-8 | B84: Fourniture cu isolé 1 x 25 | C84: ml | E84: 35 | F84: =MROUND(K84/$M$49,10) -> 7840 | G84: =E84*F84 -> 274400 | J84: 9420 | K84: 6975 | L84: =K84*E84 -> 244125
A85: 301-9 | B85: Fourniture câble cu nu 1 x25 | C85: ml | E85: 50 | F85: =MROUND(K85/$M$49,10) -> 6260 | G85: =E85*F85 -> 313000 | J85: 7530 | K85: 5575 | L85: =K85*E85 -> 278750
A86: 301-10 | B86: Fourniture protection mécanique 30/30 | C86: u | E86: 3 | F86: =MROUND(K86/$M$49,10) -> 28600 | G86: =E86*F86 -> 85800 | J86: 34360 | K86: 25450 | L86: =K86*E86 -> 76350
A87: 301-11 | B87: Fourniture piquet de terre | C87: u | E87: 9 | F87: =MROUND(K87/$M$49,10) -> 15140 | G87: =E87*F87 -> 136260 | J87: 18190 | K87: 13475 | L87: =K87*E87 -> 121275
A88: 301-12 | B88: Fourniture support béton 13-1000 | C88: u | E88: 1 | F88: =MROUND(K88/$M$49,10) -> 1404490 | G88: =E88*F88 -> 1404490 | J88: 1687500 | K88: 1250000 | L88: =K88*E88 -> 1250000
... A95: 301-19 | B95: Fourniture câble J4 | C95: ml | E95: 300 | F95: =MROUND(K95/$M$49,10) -> 2810 | G95: =E95*F95 -> 843000 | J95: 3380 | K95: 2500 | L95: =K95*E95 -> 750000
B96: confection & pose | F96: =MROUND(K96/$M$49,10) -> 0
A97: 301-20 | B97: Dépose des poteaux HT | C97: u | E97: 1 | F97: =MROUND(K97/$M$49,10) -> 112360 | G97: =E97*F97 -> 112360 | J97: 135000 | K97: 100000 | L97: =K97*E97 -> 100000
A98: 301-21 | B98: Dépose poteaux B | C98: u | E98: 18 | F98: =MROUND(K98/$M$49,10) -> 112360 | G98: =E98*F98 -> 2022480 | J98: 135000 | K98: 100000 | L98: =K98*E98 -> 1800000
A99: 301-22 | B99: Dépose câble BT | C99: ens | E99: 1 | F99: =MROUND(K99/$M$49,10) -> 842700 | G99: =E99*F99 -> 842700 | J99: 1012500 | K99: 750000 | L99: =K99*E99 -> 750000
A100: 301-23 | B100: Dépose des branchements et reprise | C100: ens | E100: 1 | F100: =MROUND(K100/$M$49,10) -> 1528090 | G100: =E100*F100 -> 1528090 | J100: 1836000 | K100: 1360000 | L100: =K100*E100 -> 1360000
A101: 301-24 | B101: Réalisation RAS HTA et dépose RAS existante | C101: ens | E101: 1 | F101: =MROUND(K101/$M$49,10) -> 337080 | G101: =E101*F101 -> 337080 | J101: 405000 | K101: 300000 | L101: =K101*E101 -> 300000
A102: 301-25 | B102: Dépose et pose DPH3 | C102: ens | E102: 1 | F102: =MROUND(K102/$M$49,10) -> 926970 | G102: =E102*F102 -> 926970 | J102: 1113750 | K102: 825000 | L102: =K102*E102 -> 825000
A103: 301-26 | B103: Dépose et pose branchement triphasé | C103: ens | E103: 1 | F103: =MROUND(K103/$M$49,10) -> 196630 | G103: =E103*F103 -> 196630 | J103: 236250 | K103: 175000 | L103: =K103*E103 -> 175000
A104: 301-27 | B104: Fouille et implantation des supports | C104: ens | E104: 1 | F104: =MROUND(K104/$M$49,10) -> 3134830 | G104: =E104*F104 -> 3134830 | J104: 3766500 | K104: 2790000 | L104: =K104*E104 -> 2790000
A105: 301-28 | B105: Confectionnement malte | C105: u | E105: 3 | F105: =MROUND(K105/$M$49,10) -> 196630 | G105: =E105*F105 -> 589890 | J105: 236250 | K105: 175000 | L105: =K105*E105 -> 525000
A106: 301-29 | B106: Transport et manutention | C106: ens | E106: 1 | F106: =MROUND(K106/$M$49,10) -> 955060 | G106: =E106*F106 -> 955060 | J106: 1147500 | K106: 850000 | L106: =K106*E106 -> 850000
A107: 301-30 | B107: Consignation et mise en service | C107: ens | E107: 1 | F107: =MROUND(K107/$M$49,10) -> 280900 | G107: =E107*F107 -> 280900 | J107: 337500 | K107: 250000 | L107: =K107*E107 -> 250000 | M107: =SUM(L76:L107) -> 30445150
A108: 302 | B108: STATION KOMO RONDPOINT MARINE NATIONALE | L108: =K108*E108 -> 0
A109: 201-0 | B109: installation + signalisation + repli | C109: Fft | E109: 1 | F109: =MROUND(K109/$M$49,10) -> 786520 | G109: =F109*E109 -> 786520 | J109: =G109 -> 786520 | K109: =300000+200000+200000 -> 700000 | L109: =K109*E109 -> 700000
A110: 302-1 | B110: Fourniture support métallique 10.440 et 10-930 de Récupération | C110: Ens | E110: 1 | F110: =MROUND(K110/$M$49,10) -> 337080 | G110: =E110*F110 -> 337080 | J110: 405000 | K110: 300000 | L110: =K110*E110 -> 300000
A111: 302-2 | B111: Fourniture câble torsadé 3 x 70 + 54,6 + 2 x 16mm² | C111: ml | E111: 550 | F111: =MROUND(K111/$M$49,10) -> 7870 | G111: =E111*F111 -> 4328500 | J111: 9450 | K111: 7000 | L111: =K111*E111 -> 3850000
...

Sheet etude pxi DV
A2: ETUDE DE PRIX Ouvrages Hydrauliques AKEMIDJOGONI
I4: brut | J4: Peines & soins | K4: cdc | L4: DS/revient | M4: VENTE/ml | N4: marge
J5: 0.1 | K5: 0.02 | M5: 1.35
I7: =SUM(G12:G58)/$E11 -> 1193956.5 | J7: =I7*$J$5 -> 119395.65 | K7: =I7*$K$5 -> 23879.13 | L7: =SUM(I7:K7) -> 1337231.3 | M7: =L7*$M$5 -> 1805262.2 | N7: =M7-L7 -> 468030.94
A9: DELTA VISION | I9: MIKA
A10: Code | B10: Désignation | C10: Unité | D10: nb | E10: Quantité | F10: Prix unitaire | G10: Prix de vente | I10: PU MIKA | J10: PT MIKA
A11: 1 | B11: Dalot OH 3 section 2*(2*1,8) / 2 chambres | C11: ml | E11: 12 | F11: 420000 | G11: 5040000 | I11: =+MROUND(M7,10) -> 1805260 | J11: =+I11*E11 -> 21663120
B12: terrassements
B13: fouilles | C13: m3 | D13: 1 | E13: =(9*17+13*5.6)/2*3.5 -> 395.15
B14: Pelle 400m3/jr fouilles | C14: u | D14: =E13/400 -> 0.987875 | E14: 1 | F14: =7500000/26 -> 288461.54 | G14: =F14*E14*D14 -> 284963.94
B15: gasoil | C15: u | D15: =100*D14 -> 98.7875 | E15: 1 | F15: 1050 | G15: =F15*E15*D15 -> 103726.88
B16: enrochement | C16: m3 | D16: 1 | E16: =17*9*1 -> 153
B17: Pelle 400m3/jr enrochement | C17: u | D17: =E16/400 -> 0.3825 | E17: 1 | F17: =7500000/26 -> 288461.54 | G17: =F17*E17*D17 -> 110336.54
B18: gasoil | C18: u | D18: =100*D17 -> 38.25 | E18: 1 | F18: 1050 | G18: =F18*E18*D18 -> 40162.5
B19: Pelle | C19: u | E19: 1 | F19: =7500000/26 -> 288461.54 | G19: =F19*E19*D19 -> 0
B20: terrassements | G20: =F20*E20*D20 -> 0
B21: terrassements | G21: =F21*E21*D21 -> 0
B22: terrassements | G22: =F22*E22*D22 -> 0
B23: MEO de gnt 0,25 13*5,6*0,10m | C23: Tonne | D23: =1.85 -> 1.85 | E23: =(13*5.6*0.1) -> 7.28 | F23: 22000 | G23: =F23*E23*D23 -> 296296
B25: béton de propreté 13*5,6*0,10m | C25: m3 | D25: 1 | E25: =13*5.6*0.1 -> 7.28 | F25: 100000 | G25: =F25*E25*D25 -> 728000
B26: geotextile | C26: rlx | D26: 1 | E26: =MROUND(SUM(E27:E28)/1080,0.0005) -> 0.188 | F26: =1050000 -> 1050000 | G26: =F26*E26*D26 -> 197400
B27: geotextile sur gnt | C27: m² | D27: 1 | E27: =13*5.6 -> 72.8
B28: geotextile sur pipe | C28: m² | D28: 1 | E28: =(2.2*2+0.5*2+4.6)*13 -> 130
B29: Flintkote | C29: kg | D29: 1 | E29: =MROUND(SUM(E27:E28)*0.4,0.0005) -> 81.12
B30: nbre de pot/ conditionnement de 25kg | C30: u | D30: 1 | E30: =ROUNDUP(E29/25,0) -> 4 | F30: 45000 | G30: =F30*E30*D30 -> 180000
B31: radier
B32: béton 4,60*12*0,2 | C32: m3 | D32: 1 | E32: =4.6*12*0.2 -> 11.04 | F32: 120000 | G32: =F32*E32*D32 -> 1324800 | I32: Type | J32: Montant/tot | K32: rep/m3/béton | L32: qté coffrage | M32: béton
B33: aciers | C33: kg | D33: 1 | E33: =82*E32 -> 905.28 | F33: =700 -> 700 | G33: =F33*E33*D33 -> 633696 | I33: Coffrage radier | J33: =SUM(G35:G37) -> 62660 | K33: =J33/E32 -> 5675.7246 | L33: =E34 -> 6.64 | M33: =E32+E39+E45 -> 35.04
B34: coffrage | C34: m² | D34: 1 | E34: =(12+4.6)*2*0.2 -> 6.64 | I34: Coffrage voiles | J34: =SUM(G42:G43) -> 362940 | K34: =J34/E39 -> 28004.63 | L34: =E41 -> 131.76
B35: cp 19mm (3,05m²) | C35: u | D35: =1/3 -> 0.33333333 | E35: =ROUNDUP(E34/3.05,0) -> 3 | F35: 22500 | G35: =F35*E35*D35 -> 22500 | I35: Coffrage tablier | J35: =SUM(G48:G50) -> 909960 | K35: =J35/E47 -> 8284.4137 | L35: =E47 -> 109.84
B36: pointes | C36: kg | D36: 1 | E36: =0.2*E34 -> 1.328 | F36: =1250 -> 1250 | G36: =F36*E36*D36 -> 1660 | J36: =SUM(J33:J35) -> 1335560 | K36: =AVERAGE(K33:K35) -> 13988.256 | L36: =SUM(L33:L35) -> 248.24
B37: chevrons | C37: u | D37: 1 | E37: =ROUNDUP(E34/1,0) -> 7 | F37: =5500 -> 5500 | G37: =F37*E37*D37 -> 38500 | I37: =E33/E32 -> 82
B38: voiles/3
B39: béton 1,8*3*0,3 * 12 | C39: m3 | D39: 1 | E39: =(1.8*0.2*E11)*3 -> 12.96 | F39: 120000 | G39: =F39*E39*D39 -> 1555200
B40: aciers | C40: kg | D40: 1 | E40: =E39*82 -> 1062.72 | F40: 700 | G40: =F40*E40*D40 -> 743904 | I40: =E40/E39 -> 82
B41: coffrage | C41: m² | D41: 1 | E41: =(1.8*12*2+1.8*0.2*2)*3 -> 131.76
B42: cp 19mm (3,05m²) | C42: m² | D42: =1/3 -> 0.33333333 | E42: =ROUNDUP(E41/3.05,0) -> 44 | F42: 22500 | G42: =F42*E42*D42 -> 330000
B43: pointes | C43: kg | D43: 1 | E43: =E41*0.2 -> 26.352 | F43: 1250 | G43: =F43*E43*D43 -> 32940
B44: Tablier | G44: =F44*E44*D44 -> 0
B45: béton 4,60*12*0,2 | C45: m3 | D45: 1 | E45: =4.6*12*0.2 -> 11.04 | F45: 120000 | G45: =F45*E45*D45 -> 1324800
B46: aciers | C46: kg | D46: 1 | E46: =82*E45 -> 905.28 | F46: =700 -> 700 | G46: =F46*E46*D46 -> 633696 | I46: =E46/E45 -> 82
B47: coffrage | C47: m² | D47: 1 | E47: =12*4.6+2*(12*2)+33.2*0.2 -> 109.84
B48: cp 19mm (3,05m²) | C48: u | D48: =1/3 -> 0.33333333 | E48: =ROUNDUP(E47/3.05,0) -> 37 | F48: 22500 | G48: =F48*E48*D48 -> 277500
B49: pointes | C49: kg | D49: 1 | E49: =0.2*E47 -> 21.968 | F49: =1250 -> 1250 | G49: =F49*E49*D49 -> 27460
B50: chevrons | C50: u | D50: 1 | E50: =ROUNDUP(E47/1,0) -> 110 | F50: =5500 -> 5500 | G50: =F50*E50*D50 -> 605000
B51: total béton B30 | C51: m3 | D51: 1 | E51: =SUM(E32,E39,E45) -> 35.04
B52: B20 | C52: M3 | E52: =+E25 -> 7.28
B53: MO Delta vision
B54: b20 | C54: m3 | D54: 1 | E54: =E52 -> 7.28 | F54: 25000 | G54: =F54*E54*D54 -> 182000
B55: b30 | C55: m3 | D55: 1 | E55: =E51 -> 35.04 | F55: 35000 | G55: =F55*E55*D55 -> 1226400
B56: aciers | C56: kg | D56: 1 | E56: =E33+E40+E46 -> 2873.28 | F56: 450 | G56: =F56*E56*D56 -> 1292976 | O56: =(2000*10)/100 -> 200
B57: coffrages | C57: m² | D57: 1 | E57: =E34+E41*D41+E47 -> 248.24 | F57: 6500 | G57: =F57*E57*D57 -> 1613560 | O57: =O56*585 -> 117000
B58: Motopompe+ carburant | C58: u | D58: =ROUNDDOWN(SUM(D14,D17,7),0) -> 8 | E58: 1 | F58: 65000 | G58: =F58*E58*D58 -> 520000
B60: ratio au m3 | C60: m3 | D60: 1 | E60: =E55 -> 35.04 | F60: =SUM(G54:G58)/SUM(E54:E55) -> 114247.07 | G60: =E60*F60 -> 4003217.3
B61: ratio au ml de 2*2*1,8( de cet ouvrage uniq.) | C61: ml | D61: 1 | E61: =E11 -> 12 | F61: =G60/E11 -> 333601.44 | G61: =F61*E61*D61 -> 4003217.3 | I61: =105000*E60 -> 3679200 | J61: =I61/E61 -> 306600
A64: 2 | B64: Dalot OH 4 section 2*(2*1,8) / 2 chambres | C64: ml | D64: 1 | E64: 12 | F64: 420000 | G64: =E64*F64 -> 5040000 | I64: Conclusion
A65: 3 | B65: Dalot OH 5 section 1,5*1,5 | C65: ml | D65: 1 | E65: 16 | F65: 195000 | G65: =E65*F65 -> 3120000 | I65: PU ouvrage au m3 | K65: =MROUND(F60,100) -> 114200
A66: 4 | B66: Dalot OH 6 section 2*(1,25*1,5) / 2 chambres | C66: ml | D66: 1 | E66: 12 | F66: 320000 | G66: =E66*F66 -> 3840000 | K66: 105000
A67: 5 | B67: Dalot OH 7 section 1*1 | C67: ml | D67: 1 | E67: 12 | F67: 175000 | G67: =E67*F67 -> 2100000 | I67: Par extrapolation | M67: volume | N67: PU | O67: PT | P67: optimisation
A68: 6 | B68: Canal 2*4 | C68: ml | D68: 1 | E68: 200 | F68: 180000 | G68: =E68*F68 -> 36000000 | I68: Dalot OH 3 section 2*(2*1,8) / 2 chambres | L68: =O68/12 -> 370300 | M68: =SUM(E32,E39,E45,E25) -> 42.32 | N68: =K66 -> 105000 | O68: =N68*M68 -> 4443600 | P68: =G11-O68 -> 596400
A69: 7 | B69: Toilettes | C69: u | D69: 1 | E69: 1 | F69: 2500000 | G69: =E69*F69 -> 2500000 | I69: Dalot OH 4 section 2*(2*1,8) / 2 chambres | L69: =O69/12 -> 370300 | M69: =M68 -> 42.32 | N69: =N68 -> 105000 | O69: =N69*M69 -> 4443600 | P69: =G11-O69 -> 596400
I70: Dalot OH 5 section 1,5*1,5 | L70: =O70/16 -> 175153.12 | M70: =2*(1.9*16*0.2)+2*(1.5*16*0.2)+2.9*17*0.1 -> 26.69 | N70: =N69 -> 105000 | O70: =N70*M70 -> 2802450 | P70: =G65-O70 -> 317550
F71: Départ | G71: =SUM(G11,G64:G69) -> 57640000 | I71: Dalot OH 6 section 2*(1,25*1,5) / 2 chambres | L71: =O71/12 -> 282275 | M71: =(3.6*12*0.2)*2+(1.25*12*0.2)*3+(4.6*13*0.1) -> 32.26 | N71: =N70 -> 105000 | O71: =N71*M71 -> 3387300 | P71: =G66-O71 -> 452700
E72: =-P80/G71 -> -0.13633904 | F72: optimisation | G72: =-P80 -> -7858582 | I72: Dalot OH 7 section 1*1 | L72: =O72/12 -> 128100 | M72: =(1.4*12*0.2)*2+(1*12*0.2)*2+(2.4*13*0.1) -> 14.64 | N72: =N71 -> 105000 | O72: =N72*M72 -> 1537200 | P72: =G67-O72 -> 562800
F73: Attérrissage | G73: =SUM(G71:G72) -> 49781418
G74: =G73*1% -> 497814.18 | I74: Canal 2*4 | M74: =4.4*200*0.2+2*(2*200*0.2)+5.4*201*0.1 -> 444.54 | N74: =MROUND(O74/M74,2500) -> 70000 | O74: =O75-O76 -> 30667268 | P74: =G68-O74 -> 5332732
F75: tps-9,5% | G75: =-G73*9.5% -> -4729234.7 | M75: =4.4*200*0.2+2*(2*200*0.2)+5.4*201*0.1 -> 444.54 | N75: =$K$65 -> 114200 | O75: =N75*M75 -> 50766468 | P75: =G68-O75 -> -14766468
F76: TOTAL TTC | G76: =+SUM(G73:G75) -> 45549997 | L76: équ.(-)dalot | M76: =176 -> 176 | N76: =$K$65 -> 114200 | O76: =N76*M76 -> 20099200 | P76: =G69-O76 -> -17599200
I78: Toilettes | M78: 1 | N78: 2500000 | O78: 2500000 | P78: =G69-O78 -> 0
B79: Team Projets
K80: 104000 | M80: Gain sur revue prix Delta Vision | P80: =SUM(P68:P74) -> 7858582

Sheet DQ ouvrages
A1: DEVIS QUANTITATIF
A2: TRAVAUX DE CONSTRUCTION D'OUVRAGES DE DRAINAGE DE LA ROUTE AKIMIDJONGONI
A5: N° PRIX | B5: DESIGNATION | C5: QUANTITE | D5: UNITE
A6: Sous total 100
A7: SECTION 100 | B7: OUVRAGES DE DRAINAGE
A8: 100.1 | B8: CANAL PRINCIPAL
B9: Travaux de réalisation d'un canal rectangulaiire de section b=1.5m h 1.5m L 130m (Vers marrine-Rond point)
A10: 100.1.1 | B10: Beton de proprété C 150 | C10: 19.5 | D10: m3 | E10: ok
A11: 100.1.2 | B11: Coffrages | C11: 585 | D11: m2
A12: 100.1.3 | B12: Aciers à haute adhérence | C12: 11466 | D12: kg
A13: 100.1.4 | B13: Béton de qualité Q 350 au ciment CPA 350 | C13: 127.4 | D13: m3
A14: 100.1.5 | B14: Réalisation des barbacanes | C14: 780 | D14: unité
A15: 100.1.7 | B15: Fouille | C15: 994.5 | D15: m2
B16: Travaux de réalisation d'un canal rectangulaire de section b=3m h 1.5m L 40m (suite-Axe Montagne sainte)
A17: 100.1.1 | B17: Beton de proprété C 150 | C17: 12 | D17: m3 | E17: ok
A18: 100.1.2 | B18: Coffrages | C18: 240 | D18: m2
A19: 100.1.3 | B19: Aciers à haute adhérence | C19: 4608 | D19: kg
A20: 100.1.4 | B20: Béton de qualité Q 350 au ciment CPA 350 | C20: 51.2 | D20: m3
A21: 100.1.5 | B21: Réalisation des barbacanes | C21: 240 | D21: unité
A22: 100.1.7 | B22: Fouille | C22: 396 | D22: m2
B23: Travaux de réalisation d'un canal rectangulaire de section b=4m h 1.8m L 360m (Montagne sainte-Patrimoine)
A24: 100.1.1 | B24: Beton de proprété C 150 | C24: 144 | D24: m3 | E24: ok
A25: 100.1.2 | B25: Coffrages | C25: 2736 | D25: m2
A26: 100.1.3 | B26: Aciers à haute adhérence | C26: 51840 | D26: kg
A27: 100.1.4 | B27: Béton de qualité Q 350 au ciment CPA 350 | C27: 576 | D27: m3
A28: 100.1.5 | B28: Réalisation des barbacanes | C28: 2160 | D28: unité
A29: 100.1.7 | B29: Fouille | C29: 5313.6 | D29: m2
A30: 1.4 | B30: Travaux de réalisation d'un canal rectangulaire de section b=4.5m h 1.8m L 165m (Patrimoine - racollement canal existant exutoire)
A31: 100.1.1 | B31: Beton de proprété C 150 | C31: 162 | D31: m3
A32: 100.1.2 | B32: Coffrages | C32: 2928.4403 | D32: m2
A33: 100.1.3 | B33: Aciers à haute adhérence | C33: 55303.925 | D33: kg
A34: 100.1.4 | B34: Béton de qualité Q 350 au ciment CPA 350 | C34: 614.48806 | D34: m3
A35: 100.1.5 | B35: Réalisation des barbacanes | C35: 2160 | D35: unité
A36: 100.1.7 | B36: Fouille | C36: 5659.9925 | D36: m2
A37: 100.2 | B37: RACORDEMENT AU CANAL PRINCIPAL(descente Montagne Sainte Axe 2) voie carrefour Léon M'BA-Rond poin (Axe 1)
A38: 2.1 | B38: Travaux de réalisation d'un canal rectangulaire de section h 1.5m et b= 2m L 35m | E38: OK
A39: 100.2.1 | B39: Beton de proprété C 150 | C39: 7 | D39: m3
A40: 100.2.2 | B40: Coffrages | C40: 175 | D40: m2
A41: 100.2.3 | B41: Aciers à haute adhérence | C41: 3402 | D41: kg
A42: 100.2.4 | B42: Béton de qualité Q 350 au ciment CPA 350 | C42: 37.8 | D42: m3
A43: 100.2.5 | B43: Réalisation des barbacanes | C43: 210 | D43: unité
A44: 100.2.7 | B44: Fouille | C44: 294 | D44: m2
B45: Travaux de réalisation d'un canal rectangulaire de section h 0.4m et b= 0.4m L 32m
A46: 100.2.1 | B46: Beton de proprété C 150 | C46: 1.28 | D46: m3 | E46: ok 2,2
A47: 100.2.2 | B47: Coffrages | C47: 38.4 | D47: m2
A48: 100.2.3 | B48: Aciers à haute adhérence | C48: 921.6 | D48: kg
A49: 100.2.4 | B49: Béton de qualité Q 350 au ciment CPA 350 | C49: 10.24 | D49: m3
A50: 100.2.5 | B50: Réalisation des barbacanes | C50: 192 | D50: unité
A51: 100.2.7 | B51: Fouille | C51: 23.04 | D51: m2
A52: 2.3 | B52: Travaux de réalisation d'un canal rectangulaire de section h 0.5m et b= 0.5m L 30m
A53: 100.2.1 | B53: Beton de proprété C 150 | C53: 1.5 | D53: m3 | E53: ok 2,3
A54: 100.2.2 | B54: Coffrages | C54: 45 | D54: m2
A55: 100.2.3 | B55: Aciers à haute adhérence | C55: 1026 | D55: kg
A56: 100.2.4 | B56: Béton de qualité Q 350 au ciment CPA 350 | C56: 11.4 | D56: m3
A57: 100.2.5 | B57: Réalisation des barbacanes | C57: 180 | D57: unité
A58: 100.2.7 | B58: Fouille | C58: 31.5 | D58: m2
A59: 100.3 | B59: AXE 1: CARREFOUR LEON M'BA-ROND POINT
A60: 3.1 | B60: Travaux de réalisation d'un canal rectangulaire de section h 0.5m et b= 0.5m L 900m
A61: 100.3.1 | B61: Beton de proprété C 150 | C61: =+'[2]CALCUL VOLUME'!C63 -> 45 | D61: m3 | E61: ok 3,1
A62: 100.3.2 | B62: Coffrages | C62: =+'[2]CALCUL VOLUME'!C66 -> 1350 | D62: m2
A63: 100.3.3 | B63: Aciers à haute adhérence | C63: =+'[2]CALCUL VOLUME'!C65 -> 30780 | D63: kg
A64: 100.3.4 | B64: Béton de qualité Q 350 au ciment CPA 350 | C64: =+'[2]CALCUL VOLUME'!C64 -> 342 | D64: m3
A65: 100.3.5 | B65: Réalisation des barbacanes | C65: =+'[2]CALCUL VOLUME'!C72 -> 5400 | D65: unité
A66: 100.3.7 | B66: Fouille | C66: =+'[2]CALCUL VOLUME'!C62 -> 945 | D66: m2
A67: 3.2 | B67: Travaux de réalisation d'un dalot de section (1.2x1.2) L 10m
A68: 100.3.1 | B68: Beton de proprété C 150 | C68: 1.2 | D68: m3 | E68: 3,2 ok
A69: 100.3.2 | B69: Coffrages | C69: 36 | D69: m2
A70: 100.3.3 | B70: Aciers à haute adhérence | C70: 720 | D70: kg
A71: 100.3.4 | B71: Béton de qualité Q 350 au ciment CPA 350 | C71: 8 | D71: m3
A72: 100.3.5 | B72: Réalisation des barbacanes | C72: 60 | D72: unité
A73: 100.3.7 | B73: Fouille | C73: 50.4 | D73: m2
A74: 3.3 | B74: Travaux de réalisation d'un canal rectangulaire de section h 0.9m et b= 0.9m L 260m
A75: 100.3.1 | B75: Beton de proprété C 150 | C75: 23.4 | D75: m3 | E75: 3,3 ok
A76: 100.3.2 | B76: Coffrages | C76: 757.23991 | D76: m2
A77: 100.3.3 | B77: Aciers à haute adhérence | C77: 15502.318 | D77: kg
A78: 100.3.4 | B78: Béton de qualité Q 350 au ciment CPA 350 | C78: 172.24798 | D78: m3
A79: 100.3.5 | B79: Réalisation des barbacanes | C79: 1560 | D79: unité
A80: 100.3.7 | B80: Fouille | C80: 821.91592 | D80: m2
A81: 3.4 | B81: Travaux de réalisation d'un dalot de section h 1.5m et b= 1.5m L 12m
A82: 100.3.1 | B82: Beton de proprété C 150 | C82: 1.8 | D82: m3
A83: 100.3.2 | B83: Coffrages | C83: 54 | D83: m2
A84: 100.3.3 | B84: Aciers à haute adhérence | C84: 1058.4 | D84: kg
A85: 100.3.4 | B85: Béton de qualité Q 350 au ciment CPA 350 | C85: 11.76 | D85: m3
A86: 100.3.5 | B86: Réalisation des barbacanes | C86: 72 | D86: unité
A87: 100.3.7 | B87: Fouille | C87: 91.8 | D87: m2
A88: 100.4 | B88: AXE 2: DESCENTE MONTAGNE SAINTE
A89: 4.1 | B89: Travaux de réalisation d'un canal rectangulaire de section h 0.5m et b= 0.5m L 155m
A90: 100.4.1 | B90: Beton de proprété C 150 | C90: =+'[2]CALCUL VOLUME'!F63 -> 7.75 | D90: m3 | E90: 4,1 ok
A91: 100.4.2 | B91: Coffrages | C91: =+'[2]CALCUL VOLUME'!F66 -> 232.5 | D91: m2
A92: 100.4.3 | B92: Aciers à haute adhérence | C92: =+'[2]CALCUL VOLUME'!F65 -> 5301 | D92: kg
A93: 100.4.4 | B93: Béton de qualité Q 350 au ciment CPA 350 | C93: =+'[2]CALCUL VOLUME'!F64 -> 58.9 | D93: m3
A94: 100.4.5 | B94: Réalisation des barbacanes | C94: =+'[2]CALCUL VOLUME'!F72 -> 930 | D94: unité
A95: 100.4.7 | B95: Fouille | C95: =+'[2]CALCUL VOLUME'!F62 -> 162.75 | D95: m2
B96: Travaux de réalisation d'un dalot de section 2(2x1.8) L 14m
A97: 100.4.1 | B97: Beton de proprété C 150 | C97: 6.3 | D97: m3 | E97: 4,2 ok
A98: 100.4.2 | B98: Coffrages | C98: 113.4 | D98: m2
A99: 100.4.3 | B99: Aciers à haute adhérence | C99: 2142 | D99: kg
A100: 100.4.4 | B100: Béton de qualité Q 350 au ciment CPA 350 | C100: 23.8 | D100: m3
A101: 100.4.5 | B101: Réalisation des barbacanes | C101: 84 | D101: unité
A102: 100.4.7 | B102: Fouille | C102: 219.24 | D102: m2
...
